mensajes/__init__.py
mensajes/despedida/__init__.py
mensajes/despedida/despedida.py
mensajes/hola/__init__.py
mensajes/hola/saludos.py
tests/__init__.py
tests/test_hola.py
Mensajes_Truqueli-5.0.dist-info/LICENSE
Mensajes_Truqueli-5.0.dist-info/METADATA
Mensajes_Truqueli-5.0.dist-info/WHEEL
Mensajes_Truqueli-5.0.dist-info/top_level.txt
Mensajes_Truqueli-5.0.dist-info/RECORD
