Metadata-Version: 2.1
Name: Mensajes-Truqueli
Version: 5.0
Summary: Un paquete para enviar mensajes
Author: Diego Altamirano
Author-email: diego@hola.com
Classifier: Environment :: Console
Classifier: License :: OSI Approved :: MIT License
Classifier: Programming Language :: Python
License-File: LICENSE
Requires-Dist: numpy >=1.26.4
